honeypot.py
honeypot-0.1.1.dist-info/LICENSE.txt
honeypot-0.1.1.dist-info/METADATA
honeypot-0.1.1.dist-info/WHEEL
honeypot-0.1.1.dist-info/entry_points.txt
honeypot-0.1.1.dist-info/top_level.txt
honeypot-0.1.1.dist-info/RECORD
